{"path":"working-at-deeson/charity-volunteering","templateID":0,"sharedPropsHashes":{"menuItems":"2n0Nyl"},"localProps":{"page":{"id":"W7foqhQAAC0Aflro","type":"page","slug":"working-at-deeson/charity-volunteering","title":"Charity work and volunteering","content":"<h1>Charity work and volunteering.</h1><p>We believe that it&#39;s valuable for team members and their communities to be able to spend some time volunteering for a charity or good cause.</p><p>We provide up to three days per calendar year of paid time off to team members who want to do this.</p><h2>How it works.</h2><ul><li>You must be volunteering for a registered charity or an organisation that operates by comparable principles.</li><li>You need to let colleagues know what you intend to do and what you actually did. This is to encourage others and give insight. You may be asked to write a blog to illustrate the activity.</li><li>There are up to three charity days per calendar year per person.</li><li>For new team members joining Deeson, the three days is applied pro rata in their first year.</li><li>The activity should be discussed with your line manager in advance and recorded in Bamboo.</li></ul><p><em>This information is for team members employed by Deeson Group Ltd and Deeson Publishing Ltd.</em></p>","lastModified":"2018-10-05T22:41:51+0000"}}}
